{
  "entries": [
    {
      "name": "ErrConnectCode",
      "old_code": "11000",
      "code": "11000",
      "code_is_literal": true,
      "code_is_int": true,
      "path": "broker/nats/error.go"
    },
    {
      "name": "ErrEncodedConnCode",
      "old_code": "11000",
      "code": "11000",
      "code_is_literal": true,
      "code_is_int": true,
      "path": "broker/nats/error.go"
    },
    {
      "name": "ErrPublishCode",
      "old_code": "11001",
      "code": "11001",
      "code_is_literal": true,
      "code_is_int": true,
      "path": "broker/nats/error.go"
    },
    {
      "name": "ErrPublishRequestCode",
      "old_code": "11001",
      "code": "11001",
      "code_is_literal": true,
      "code_is_int": true,
      "path": "broker/nats/error.go"
    },
    {
      "name": "ErrQueueSubscribeCode",
      "old_code": "11001",
      "code": "11001",
      "code_is_literal": true,
      "code_is_int": true,
      "path": "broker/nats/error.go"
    },
    {
      "name": "ErrEmptyConfigCode",
      "old_code": "11055",
      "code": "11055",
      "code_is_literal": true,
      "code_is_int": true,
      "path": "config/error.go"
    },
    {
      "name": "ErrViperCode",
      "old_code": "11056",
      "code": "11056",
      "code_is_literal": true,
      "code_is_int": true,
      "path": "config/error.go"
    },
    {
      "name": "ErrInMemCode",
      "old_code": "11057",
      "code": "11057",
      "code_is_literal": true,
      "code_is_int": true,
      "path": "config/error.go"
    },
    {
      "name": "ErrEmptyConfig",
      "old_code": "",
      "code": "",
      "code_is_literal": false,
      "code_is_int": false,
      "path": "config/error.go"
    },
    {
      "name": "ErrNoneDatabaseCode",
      "old_code": "11010",
      "code": "11010",
      "code_is_literal": true,
      "code_is_int": true,
      "path": "database/error.go"
    },
    {
      "name": "ErrDatabaseOpenCode",
      "old_code": "11011",
      "code": "11011",
      "code_is_literal": true,
      "code_is_int": true,
      "path": "database/error.go"
    },
    {
      "name": "ErrSQLMapUnmarshalJSONCode",
      "old_code": "11012",
      "code": "11012",
      "code_is_literal": true,
      "code_is_int": true,
      "path": "database/error.go"
    },
    {
      "name": "ErrSQLMapUnmarshalTextCode",
      "old_code": "11013",
      "code": "11013",
      "code_is_literal": true,
      "code_is_int": true,
      "path": "database/error.go"
    },
    {
      "name": "ErrSQLMapMarshalValueCode",
      "old_code": "11014",
      "code": "11014",
      "code_is_literal": true,
      "code_is_int": true,
      "path": "database/error.go"
    },
    {
      "name": "ErrSQLMapUnmarshalScannedCode",
      "old_code": "11015",
      "code": "11015",
      "code_is_literal": true,
      "code_is_int": true,
      "path": "database/error.go"
    },
    {
      "name": "ErrSQLMapInvalidScanCode",
      "old_code": "11016",
      "code": "11016",
      "code_is_literal": true,
      "code_is_int": true,
      "path": "database/error.go"
    },
    {
      "name": "ErrNoneDatabase",
      "old_code": "",
      "code": "",
      "code_is_literal": false,
      "code_is_int": false,
      "path": "database/error.go"
    },
    {
      "name": "ErrSQLMapInvalidScan",
      "old_code": "",
      "code": "",
      "code_is_literal": false,
      "code_is_int": false,
      "path": "database/error.go"
    },
    {
      "name": "ErrUnmarshalCode",
      "old_code": "11043",
      "code": "11043",
      "code_is_literal": true,
      "code_is_int": true,
      "path": "utils/error.go"
    },
    {
      "name": "ErrUnmarshalInvalidCode",
      "old_code": "11044",
      "code": "11044",
      "code_is_literal": true,
      "code_is_int": true,
      "path": "utils/error.go"
    },
    {
      "name": "ErrUnmarshalSyntaxCode",
      "old_code": "11045",
      "code": "11045",
      "code_is_literal": true,
      "code_is_int": true,
      "path": "utils/error.go"
    },
    {
      "name": "ErrUnmarshalTypeCode",
      "old_code": "11046",
      "code": "11046",
      "code_is_literal": true,
      "code_is_int": true,
      "path": "utils/error.go"
    },
    {
      "name": "ErrUnmarshalUnsupportedTypeCode",
      "old_code": "11047",
      "code": "11047",
      "code_is_literal": true,
      "code_is_int": true,
      "path": "utils/error.go"
    },
    {
      "name": "ErrUnmarshalUnsupportedValueCode",
      "old_code": "11048",
      "code": "11048",
      "code_is_literal": true,
      "code_is_int": true,
      "path": "utils/error.go"
    },
    {
      "name": "ErrMarshalCode",
      "old_code": "11049",
      "code": "11049",
      "code_is_literal": true,
      "code_is_int": true,
      "path": "utils/error.go"
    },
    {
      "name": "ErrGetBoolCode",
      "old_code": "11050",
      "code": "11050",
      "code_is_literal": true,
      "code_is_int": true,
      "path": "utils/error.go"
    },
    {
      "name": "ErrInvalidProtocolCode",
      "old_code": "11051",
      "code": "11051",
      "code_is_literal": true,
      "code_is_int": true,
      "path": "utils/error.go"
    },
    {
      "name": "ErrRemoteFileNotFoundCode",
      "old_code": "11052",
      "code": "11052",
      "code_is_literal": true,
      "code_is_int": true,
      "path": "utils/error.go"
    },
    {
      "name": "ErrReadingRemoteFileCode",
      "old_code": "11053",
      "code": "11053",
      "code_is_literal": true,
      "code_is_int": true,
      "path": "utils/error.go"
    },
    {
      "name": "ErrReadingLocalFileCode",
      "old_code": "11054",
      "code": "11054",
      "code_is_literal": true,
      "code_is_int": true,
      "path": "utils/error.go"
    },
    {
      "name": "ErrInvalidProtocol",
      "old_code": "",
      "code": "",
      "code_is_literal": false,
      "code_is_int": false,
      "path": "utils/error.go"
    },
    {
      "name": "ErrApplyManifestCode",
      "old_code": "11021",
      "code": "11021",
      "code_is_literal": true,
      "code_is_int": true,
      "path": "utils/kubernetes/error.go"
    },
    {
      "name": "ErrServiceDiscoveryCode",
      "old_code": "11022",
      "code": "11022",
      "code_is_literal": true,
      "code_is_int": true,
      "path": "utils/kubernetes/error.go"
    },
    {
      "name": "ErrApplyHelmChartCode",
      "old_code": "11023",
      "code": "11023",
      "code_is_literal": true,
      "code_is_int": true,
      "path": "utils/kubernetes/error.go"
    },
    {
      "name": "ErrNewKubeClientCode",
      "old_code": "11024",
      "code": "11024",
      "code_is_literal": true,
      "code_is_int": true,
      "path": "utils/kubernetes/error.go"
    },
    {
      "name": "ErrNewDynClientCode",
      "old_code": "11025",
      "code": "11025",
      "code_is_literal": true,
      "code_is_int": true,
      "path": "utils/kubernetes/error.go"
    },
    {
      "name": "ErrNewDiscoveryCode",
      "old_code": "11026",
      "code": "11026",
      "code_is_literal": true,
      "code_is_int": true,
      "path": "utils/kubernetes/error.go"
    },
    {
      "name": "ErrNewInformerCode",
      "old_code": "11027",
      "code": "11027",
      "code_is_literal": true,
      "code_is_int": true,
      "path": "utils/kubernetes/error.go"
    },
    {
      "name": "ErrEndpointNotFoundCode",
      "old_code": "11028",
      "code": "11028",
      "code_is_literal": true,
      "code_is_int": true,
      "path": "utils/kubernetes/error.go"
    },
    {
      "name": "ErrInvalidAPIServerCode",
      "old_code": "11029",
      "code": "11029",
      "code_is_literal": true,
      "code_is_int": true,
      "path": "utils/kubernetes/error.go"
    },
    {
      "name": "ErrLoadConfigCode",
      "old_code": "11030",
      "code": "11030",
      "code_is_literal": true,
      "code_is_int": true,
      "path": "utils/kubernetes/error.go"
    },
    {
      "name": "ErrValidateConfigCode",
      "old_code": "11031",
      "code": "11031",
      "code_is_literal": true,
      "code_is_int": true,
      "path": "utils/kubernetes/error.go"
    },
    {
      "name": "ErrEndpointNotFound",
      "old_code": "",
      "code": "",
      "code_is_literal": false,
      "code_is_int": false,
      "path": "utils/kubernetes/error.go"
    },
    {
      "name": "ErrInvalidAPIServer",
      "old_code": "",
      "code": "",
      "code_is_literal": false,
      "code_is_int": false,
      "path": "utils/kubernetes/error.go"
    },
    {
      "name": "ErrExposeResourceCode",
      "old_code": "11032",
      "code": "11032",
      "code_is_literal": true,
      "code_is_int": true,
      "path": "utils/kubernetes/expose/error.go"
    },
    {
      "name": "ErrGettingResourceCode",
      "old_code": "11033",
      "code": "11033",
      "code_is_literal": true,
      "code_is_int": true,
      "path": "utils/kubernetes/expose/error.go"
    },
    {
      "name": "ErrTraverserCode",
      "old_code": "11034",
      "code": "11034",
      "code_is_literal": true,
      "code_is_int": true,
      "path": "utils/kubernetes/expose/error.go"
    },
    {
      "name": "ErrResourceCannotBeExposedCode",
      "old_code": "11035",
      "code": "11035",
      "code_is_literal": true,
      "code_is_int": true,
      "path": "utils/kubernetes/expose/error.go"
    },
    {
      "name": "ErrSelectorBasedMapCode",
      "old_code": "11036",
      "code": "11036",
      "code_is_literal": true,
      "code_is_int": true,
      "path": "utils/kubernetes/expose/error.go"
    },
    {
      "name": "ErrProtocolBasedMapCode",
      "old_code": "11037",
      "code": "11037",
      "code_is_literal": true,
      "code_is_int": true,
      "path": "utils/kubernetes/expose/error.go"
    },
    {
      "name": "ErrLableBasedMapCode",
      "old_code": "11038",
      "code": "11038",
      "code_is_literal": true,
      "code_is_int": true,
      "path": "utils/kubernetes/expose/error.go"
    },
    {
      "name": "ErrPortParsingCode",
      "old_code": "11039",
      "code": "11039",
      "code_is_literal": true,
      "code_is_int": true,
      "path": "utils/kubernetes/expose/error.go"
    },
    {
      "name": "ErrGenerateServiceCode",
      "old_code": "11040",
      "code": "11040",
      "code_is_literal": true,
      "code_is_int": true,
      "path": "utils/kubernetes/expose/error.go"
    },
    {
      "name": "ErrConstructingRestHelperCode",
      "old_code": "11041",
      "code": "11041",
      "code_is_literal": true,
      "code_is_int": true,
      "path": "utils/kubernetes/expose/error.go"
    },
    {
      "name": "ErrCreatingServiceCode",
      "old_code": "11042",
      "code": "11042",
      "code_is_literal": true,
      "code_is_int": true,
      "path": "utils/kubernetes/expose/error.go"
    },
    {
      "name": "ErrPodHasNoLabelsCode",
      "old_code": "11058",
      "code": "11058",
      "code_is_literal": true,
      "code_is_int": true,
      "path": "utils/kubernetes/expose/error.go"
    },
    {
      "name": "ErrServiceHasNoSelectorsCode",
      "old_code": "11059",
      "code": "11059",
      "code_is_literal": true,
      "code_is_int": true,
      "path": "utils/kubernetes/expose/error.go"
    },
    {
      "name": "ErrInvalidDeploymentNoSelectorsLabelsCode",
      "old_code": "11060",
      "code": "11060",
      "code_is_literal": true,
      "code_is_int": true,
      "path": "utils/kubernetes/expose/error.go"
    },
    {
      "name": "ErrInvalidDeploymentNoSelectorsCode",
      "old_code": "11061",
      "code": "11061",
      "code_is_literal": true,
      "code_is_int": true,
      "path": "utils/kubernetes/expose/error.go"
    },
    {
      "name": "ErrInvalidReplicaNoSelectorsLabelsCode",
      "old_code": "11062",
      "code": "11062",
      "code_is_literal": true,
      "code_is_int": true,
      "path": "utils/kubernetes/expose/error.go"
    },
    {
      "name": "ErrInvalidReplicaSetNoSelectorsCode",
      "old_code": "11063",
      "code": "11063",
      "code_is_literal": true,
      "code_is_int": true,
      "path": "utils/kubernetes/expose/error.go"
    },
    {
      "name": "ErrNoPortsFoundForHeadlessResourceCode",
      "old_code": "11064",
      "code": "11064",
      "code_is_literal": true,
      "code_is_int": true,
      "path": "utils/kubernetes/expose/error.go"
    },
    {
      "name": "ErrUnknownSessionAffinityErrCode",
      "old_code": "11065",
      "code": "11065",
      "code_is_literal": true,
      "code_is_int": true,
      "path": "utils/kubernetes/expose/error.go"
    },
    {
      "name": "ErrMatchExpressionsConvertionErrCode",
      "old_code": "11066",
      "code": "11066",
      "code_is_literal": true,
      "code_is_int": true,
      "path": "utils/kubernetes/expose/error.go"
    },
    {
      "name": "ErrFailedToExtractPodSelectorErrCode",
      "old_code": "11067",
      "code": "11067",
      "code_is_literal": true,
      "code_is_int": true,
      "path": "utils/kubernetes/expose/error.go"
    },
    {
      "name": "ErrFailedToExtractPortsCode",
      "old_code": "11068",
      "code": "11068",
      "code_is_literal": true,
      "code_is_int": true,
      "path": "utils/kubernetes/expose/error.go"
    },
    {
      "name": "ErrFailedToExtractProtocolsErrCode",
      "old_code": "11069",
      "code": "11069",
      "code_is_literal": true,
      "code_is_int": true,
      "path": "utils/kubernetes/expose/error.go"
    },
    {
      "name": "ErrCannotExposeObjectErrCode",
      "old_code": "11070",
      "code": "11070",
      "code_is_literal": true,
      "code_is_int": true,
      "path": "utils/kubernetes/expose/error.go"
    },
    {
      "name": "ErrPodHasNoLabels",
      "old_code": "",
      "code": "",
      "code_is_literal": false,
      "code_is_int": false,
      "path": "utils/kubernetes/expose/error.go"
    },
    {
      "name": "ErrServiceHasNoSelectors",
      "old_code": "",
      "code": "",
      "code_is_literal": false,
      "code_is_int": false,
      "path": "utils/kubernetes/expose/error.go"
    },
    {
      "name": "ErrInvalidDeploymentNoSelectorsLabels",
      "old_code": "",
      "code": "",
      "code_is_literal": false,
      "code_is_int": false,
      "path": "utils/kubernetes/expose/error.go"
    },
    {
      "name": "ErrInvalidDeploymentNoSelectors",
      "old_code": "",
      "code": "",
      "code_is_literal": false,
      "code_is_int": false,
      "path": "utils/kubernetes/expose/error.go"
    },
    {
      "name": "ErrInvalidReplicaNoSelectorsLabels",
      "old_code": "",
      "code": "",
      "code_is_literal": false,
      "code_is_int": false,
      "path": "utils/kubernetes/expose/error.go"
    },
    {
      "name": "ErrInvalidReplicaSetNoSelectors",
      "old_code": "",
      "code": "",
      "code_is_literal": false,
      "code_is_int": false,
      "path": "utils/kubernetes/expose/error.go"
    },
    {
      "name": "ErrNoPortsFoundForHeadlessResource",
      "old_code": "",
      "code": "",
      "code_is_literal": false,
      "code_is_int": false,
      "path": "utils/kubernetes/expose/error.go"
    }
  ],
  "literal_codes": {
    "11000": [
      {
        "name": "ErrConnectCode",
        "old_code": "11000",
        "code": "11000",
        "code_is_literal": true,
        "code_is_int": true,
        "path": "broker/nats/error.go"
      },
      {
        "name": "ErrEncodedConnCode",
        "old_code": "11000",
        "code": "11000",
        "code_is_literal": true,
        "code_is_int": true,
        "path": "broker/nats/error.go"
      }
    ],
    "11001": [
      {
        "name": "ErrPublishCode",
        "old_code": "11001",
        "code": "11001",
        "code_is_literal": true,
        "code_is_int": true,
        "path": "broker/nats/error.go"
      },
      {
        "name": "ErrPublishRequestCode",
        "old_code": "11001",
        "code": "11001",
        "code_is_literal": true,
        "code_is_int": true,
        "path": "broker/nats/error.go"
      },
      {
        "name": "ErrQueueSubscribeCode",
        "old_code": "11001",
        "code": "11001",
        "code_is_literal": true,
        "code_is_int": true,
        "path": "broker/nats/error.go"
      }
    ],
    "11010": [
      {
        "name": "ErrNoneDatabaseCode",
        "old_code": "11010",
        "code": "11010",
        "code_is_literal": true,
        "code_is_int": true,
        "path": "database/error.go"
      }
    ],
    "11011": [
      {
        "name": "ErrDatabaseOpenCode",
        "old_code": "11011",
        "code": "11011",
        "code_is_literal": true,
        "code_is_int": true,
        "path": "database/error.go"
      }
    ],
    "11012": [
      {
        "name": "ErrSQLMapUnmarshalJSONCode",
        "old_code": "11012",
        "code": "11012",
        "code_is_literal": true,
        "code_is_int": true,
        "path": "database/error.go"
      }
    ],
    "11013": [
      {
        "name": "ErrSQLMapUnmarshalTextCode",
        "old_code": "11013",
        "code": "11013",
        "code_is_literal": true,
        "code_is_int": true,
        "path": "database/error.go"
      }
    ],
    "11014": [
      {
        "name": "ErrSQLMapMarshalValueCode",
        "old_code": "11014",
        "code": "11014",
        "code_is_literal": true,
        "code_is_int": true,
        "path": "database/error.go"
      }
    ],
    "11015": [
      {
        "name": "ErrSQLMapUnmarshalScannedCode",
        "old_code": "11015",
        "code": "11015",
        "code_is_literal": true,
        "code_is_int": true,
        "path": "database/error.go"
      }
    ],
    "11016": [
      {
        "name": "ErrSQLMapInvalidScanCode",
        "old_code": "11016",
        "code": "11016",
        "code_is_literal": true,
        "code_is_int": true,
        "path": "database/error.go"
      }
    ],
    "11021": [
      {
        "name": "ErrApplyManifestCode",
        "old_code": "11021",
        "code": "11021",
        "code_is_literal": true,
        "code_is_int": true,
        "path": "utils/kubernetes/error.go"
      }
    ],
    "11022": [
      {
        "name": "ErrServiceDiscoveryCode",
        "old_code": "11022",
        "code": "11022",
        "code_is_literal": true,
        "code_is_int": true,
        "path": "utils/kubernetes/error.go"
      }
    ],
    "11023": [
      {
        "name": "ErrApplyHelmChartCode",
        "old_code": "11023",
        "code": "11023",
        "code_is_literal": true,
        "code_is_int": true,
        "path": "utils/kubernetes/error.go"
      }
    ],
    "11024": [
      {
        "name": "ErrNewKubeClientCode",
        "old_code": "11024",
        "code": "11024",
        "code_is_literal": true,
        "code_is_int": true,
        "path": "utils/kubernetes/error.go"
      }
    ],
    "11025": [
      {
        "name": "ErrNewDynClientCode",
        "old_code": "11025",
        "code": "11025",
        "code_is_literal": true,
        "code_is_int": true,
        "path": "utils/kubernetes/error.go"
      }
    ],
    "11026": [
      {
        "name": "ErrNewDiscoveryCode",
        "old_code": "11026",
        "code": "11026",
        "code_is_literal": true,
        "code_is_int": true,
        "path": "utils/kubernetes/error.go"
      }
    ],
    "11027": [
      {
        "name": "ErrNewInformerCode",
        "old_code": "11027",
        "code": "11027",
        "code_is_literal": true,
        "code_is_int": true,
        "path": "utils/kubernetes/error.go"
      }
    ],
    "11028": [
      {
        "name": "ErrEndpointNotFoundCode",
        "old_code": "11028",
        "code": "11028",
        "code_is_literal": true,
        "code_is_int": true,
        "path": "utils/kubernetes/error.go"
      }
    ],
    "11029": [
      {
        "name": "ErrInvalidAPIServerCode",
        "old_code": "11029",
        "code": "11029",
        "code_is_literal": true,
        "code_is_int": true,
        "path": "utils/kubernetes/error.go"
      }
    ],
    "11030": [
      {
        "name": "ErrLoadConfigCode",
        "old_code": "11030",
        "code": "11030",
        "code_is_literal": true,
        "code_is_int": true,
        "path": "utils/kubernetes/error.go"
      }
    ],
    "11031": [
      {
        "name": "ErrValidateConfigCode",
        "old_code": "11031",
        "code": "11031",
        "code_is_literal": true,
        "code_is_int": true,
        "path": "utils/kubernetes/error.go"
      }
    ],
    "11032": [
      {
        "name": "ErrExposeResourceCode",
        "old_code": "11032",
        "code": "11032",
        "code_is_literal": true,
        "code_is_int": true,
        "path": "utils/kubernetes/expose/error.go"
      }
    ],
    "11033": [
      {
        "name": "ErrGettingResourceCode",
        "old_code": "11033",
        "code": "11033",
        "code_is_literal": true,
        "code_is_int": true,
        "path": "utils/kubernetes/expose/error.go"
      }
    ],
    "11034": [
      {
        "name": "ErrTraverserCode",
        "old_code": "11034",
        "code": "11034",
        "code_is_literal": true,
        "code_is_int": true,
        "path": "utils/kubernetes/expose/error.go"
      }
    ],
    "11035": [
      {
        "name": "ErrResourceCannotBeExposedCode",
        "old_code": "11035",
        "code": "11035",
        "code_is_literal": true,
        "code_is_int": true,
        "path": "utils/kubernetes/expose/error.go"
      }
    ],
    "11036": [
      {
        "name": "ErrSelectorBasedMapCode",
        "old_code": "11036",
        "code": "11036",
        "code_is_literal": true,
        "code_is_int": true,
        "path": "utils/kubernetes/expose/error.go"
      }
    ],
    "11037": [
      {
        "name": "ErrProtocolBasedMapCode",
        "old_code": "11037",
        "code": "11037",
        "code_is_literal": true,
        "code_is_int": true,
        "path": "utils/kubernetes/expose/error.go"
      }
    ],
    "11038": [
      {
        "name": "ErrLableBasedMapCode",
        "old_code": "11038",
        "code": "11038",
        "code_is_literal": true,
        "code_is_int": true,
        "path": "utils/kubernetes/expose/error.go"
      }
    ],
    "11039": [
      {
        "name": "ErrPortParsingCode",
        "old_code": "11039",
        "code": "11039",
        "code_is_literal": true,
        "code_is_int": true,
        "path": "utils/kubernetes/expose/error.go"
      }
    ],
    "11040": [
      {
        "name": "ErrGenerateServiceCode",
        "old_code": "11040",
        "code": "11040",
        "code_is_literal": true,
        "code_is_int": true,
        "path": "utils/kubernetes/expose/error.go"
      }
    ],
    "11041": [
      {
        "name": "ErrConstructingRestHelperCode",
        "old_code": "11041",
        "code": "11041",
        "code_is_literal": true,
        "code_is_int": true,
        "path": "utils/kubernetes/expose/error.go"
      }
    ],
    "11042": [
      {
        "name": "ErrCreatingServiceCode",
        "old_code": "11042",
        "code": "11042",
        "code_is_literal": true,
        "code_is_int": true,
        "path": "utils/kubernetes/expose/error.go"
      }
    ],
    "11043": [
      {
        "name": "ErrUnmarshalCode",
        "old_code": "11043",
        "code": "11043",
        "code_is_literal": true,
        "code_is_int": true,
        "path": "utils/error.go"
      }
    ],
    "11044": [
      {
        "name": "ErrUnmarshalInvalidCode",
        "old_code": "11044",
        "code": "11044",
        "code_is_literal": true,
        "code_is_int": true,
        "path": "utils/error.go"
      }
    ],
    "11045": [
      {
        "name": "ErrUnmarshalSyntaxCode",
        "old_code": "11045",
        "code": "11045",
        "code_is_literal": true,
        "code_is_int": true,
        "path": "utils/error.go"
      }
    ],
    "11046": [
      {
        "name": "ErrUnmarshalTypeCode",
        "old_code": "11046",
        "code": "11046",
        "code_is_literal": true,
        "code_is_int": true,
        "path": "utils/error.go"
      }
    ],
    "11047": [
      {
        "name": "ErrUnmarshalUnsupportedTypeCode",
        "old_code": "11047",
        "code": "11047",
        "code_is_literal": true,
        "code_is_int": true,
        "path": "utils/error.go"
      }
    ],
    "11048": [
      {
        "name": "ErrUnmarshalUnsupportedValueCode",
        "old_code": "11048",
        "code": "11048",
        "code_is_literal": true,
        "code_is_int": true,
        "path": "utils/error.go"
      }
    ],
    "11049": [
      {
        "name": "ErrMarshalCode",
        "old_code": "11049",
        "code": "11049",
        "code_is_literal": true,
        "code_is_int": true,
        "path": "utils/error.go"
      }
    ],
    "11050": [
      {
        "name": "ErrGetBoolCode",
        "old_code": "11050",
        "code": "11050",
        "code_is_literal": true,
        "code_is_int": true,
        "path": "utils/error.go"
      }
    ],
    "11051": [
      {
        "name": "ErrInvalidProtocolCode",
        "old_code": "11051",
        "code": "11051",
        "code_is_literal": true,
        "code_is_int": true,
        "path": "utils/error.go"
      }
    ],
    "11052": [
      {
        "name": "ErrRemoteFileNotFoundCode",
        "old_code": "11052",
        "code": "11052",
        "code_is_literal": true,
        "code_is_int": true,
        "path": "utils/error.go"
      }
    ],
    "11053": [
      {
        "name": "ErrReadingRemoteFileCode",
        "old_code": "11053",
        "code": "11053",
        "code_is_literal": true,
        "code_is_int": true,
        "path": "utils/error.go"
      }
    ],
    "11054": [
      {
        "name": "ErrReadingLocalFileCode",
        "old_code": "11054",
        "code": "11054",
        "code_is_literal": true,
        "code_is_int": true,
        "path": "utils/error.go"
      }
    ],
    "11055": [
      {
        "name": "ErrEmptyConfigCode",
        "old_code": "11055",
        "code": "11055",
        "code_is_literal": true,
        "code_is_int": true,
        "path": "config/error.go"
      }
    ],
    "11056": [
      {
        "name": "ErrViperCode",
        "old_code": "11056",
        "code": "11056",
        "code_is_literal": true,
        "code_is_int": true,
        "path": "config/error.go"
      }
    ],
    "11057": [
      {
        "name": "ErrInMemCode",
        "old_code": "11057",
        "code": "11057",
        "code_is_literal": true,
        "code_is_int": true,
        "path": "config/error.go"
      }
    ],
    "11058": [
      {
        "name": "ErrPodHasNoLabelsCode",
        "old_code": "11058",
        "code": "11058",
        "code_is_literal": true,
        "code_is_int": true,
        "path": "utils/kubernetes/expose/error.go"
      }
    ],
    "11059": [
      {
        "name": "ErrServiceHasNoSelectorsCode",
        "old_code": "11059",
        "code": "11059",
        "code_is_literal": true,
        "code_is_int": true,
        "path": "utils/kubernetes/expose/error.go"
      }
    ],
    "11060": [
      {
        "name": "ErrInvalidDeploymentNoSelectorsLabelsCode",
        "old_code": "11060",
        "code": "11060",
        "code_is_literal": true,
        "code_is_int": true,
        "path": "utils/kubernetes/expose/error.go"
      }
    ],
    "11061": [
      {
        "name": "ErrInvalidDeploymentNoSelectorsCode",
        "old_code": "11061",
        "code": "11061",
        "code_is_literal": true,
        "code_is_int": true,
        "path": "utils/kubernetes/expose/error.go"
      }
    ],
    "11062": [
      {
        "name": "ErrInvalidReplicaNoSelectorsLabelsCode",
        "old_code": "11062",
        "code": "11062",
        "code_is_literal": true,
        "code_is_int": true,
        "path": "utils/kubernetes/expose/error.go"
      }
    ],
    "11063": [
      {
        "name": "ErrInvalidReplicaSetNoSelectorsCode",
        "old_code": "11063",
        "code": "11063",
        "code_is_literal": true,
        "code_is_int": true,
        "path": "utils/kubernetes/expose/error.go"
      }
    ],
    "11064": [
      {
        "name": "ErrNoPortsFoundForHeadlessResourceCode",
        "old_code": "11064",
        "code": "11064",
        "code_is_literal": true,
        "code_is_int": true,
        "path": "utils/kubernetes/expose/error.go"
      }
    ],
    "11065": [
      {
        "name": "ErrUnknownSessionAffinityErrCode",
        "old_code": "11065",
        "code": "11065",
        "code_is_literal": true,
        "code_is_int": true,
        "path": "utils/kubernetes/expose/error.go"
      }
    ],
    "11066": [
      {
        "name": "ErrMatchExpressionsConvertionErrCode",
        "old_code": "11066",
        "code": "11066",
        "code_is_literal": true,
        "code_is_int": true,
        "path": "utils/kubernetes/expose/error.go"
      }
    ],
    "11067": [
      {
        "name": "ErrFailedToExtractPodSelectorErrCode",
        "old_code": "11067",
        "code": "11067",
        "code_is_literal": true,
        "code_is_int": true,
        "path": "utils/kubernetes/expose/error.go"
      }
    ],
    "11068": [
      {
        "name": "ErrFailedToExtractPortsCode",
        "old_code": "11068",
        "code": "11068",
        "code_is_literal": true,
        "code_is_int": true,
        "path": "utils/kubernetes/expose/error.go"
      }
    ],
    "11069": [
      {
        "name": "ErrFailedToExtractProtocolsErrCode",
        "old_code": "11069",
        "code": "11069",
        "code_is_literal": true,
        "code_is_int": true,
        "path": "utils/kubernetes/expose/error.go"
      }
    ],
    "11070": [
      {
        "name": "ErrCannotExposeObjectErrCode",
        "old_code": "11070",
        "code": "11070",
        "code_is_literal": true,
        "code_is_int": true,
        "path": "utils/kubernetes/expose/error.go"
      }
    ]
  },
  "call_expr_codes": [
    {
      "name": "ErrEmptyConfig",
      "old_code": "",
      "code": "",
      "code_is_literal": false,
      "code_is_int": false,
      "path": "config/error.go"
    },
    {
      "name": "ErrNoneDatabase",
      "old_code": "",
      "code": "",
      "code_is_literal": false,
      "code_is_int": false,
      "path": "database/error.go"
    },
    {
      "name": "ErrSQLMapInvalidScan",
      "old_code": "",
      "code": "",
      "code_is_literal": false,
      "code_is_int": false,
      "path": "database/error.go"
    },
    {
      "name": "ErrInvalidProtocol",
      "old_code": "",
      "code": "",
      "code_is_literal": false,
      "code_is_int": false,
      "path": "utils/error.go"
    },
    {
      "name": "ErrEndpointNotFound",
      "old_code": "",
      "code": "",
      "code_is_literal": false,
      "code_is_int": false,
      "path": "utils/kubernetes/error.go"
    },
    {
      "name": "ErrInvalidAPIServer",
      "old_code": "",
      "code": "",
      "code_is_literal": false,
      "code_is_int": false,
      "path": "utils/kubernetes/error.go"
    },
    {
      "name": "ErrPodHasNoLabels",
      "old_code": "",
      "code": "",
      "code_is_literal": false,
      "code_is_int": false,
      "path": "utils/kubernetes/expose/error.go"
    },
    {
      "name": "ErrServiceHasNoSelectors",
      "old_code": "",
      "code": "",
      "code_is_literal": false,
      "code_is_int": false,
      "path": "utils/kubernetes/expose/error.go"
    },
    {
      "name": "ErrInvalidDeploymentNoSelectorsLabels",
      "old_code": "",
      "code": "",
      "code_is_literal": false,
      "code_is_int": false,
      "path": "utils/kubernetes/expose/error.go"
    },
    {
      "name": "ErrInvalidDeploymentNoSelectors",
      "old_code": "",
      "code": "",
      "code_is_literal": false,
      "code_is_int": false,
      "path": "utils/kubernetes/expose/error.go"
    },
    {
      "name": "ErrInvalidReplicaNoSelectorsLabels",
      "old_code": "",
      "code": "",
      "code_is_literal": false,
      "code_is_int": false,
      "path": "utils/kubernetes/expose/error.go"
    },
    {
      "name": "ErrInvalidReplicaSetNoSelectors",
      "old_code": "",
      "code": "",
      "code_is_literal": false,
      "code_is_int": false,
      "path": "utils/kubernetes/expose/error.go"
    },
    {
      "name": "ErrNoPortsFoundForHeadlessResource",
      "old_code": "",
      "code": "",
      "code_is_literal": false,
      "code_is_int": false,
      "path": "utils/kubernetes/expose/error.go"
    }
  ],
  "deprecated_new_default": null,
  "errors_raw": {
    "ErrApplyHelmChartCode": [
      {
        "name": "ErrApplyHelmChartCode",
        "code": "",
        "severity": "Alert",
        "long_description": "",
        "short_description": "Error applying helm chart",
        "probable_cause": "",
        "suggested_remediation": ""
      }
    ],
    "ErrApplyManifestCode": [
      {
        "name": "ErrApplyManifestCode",
        "code": "",
        "severity": "Alert",
        "long_description": "",
        "short_description": "Error Applying manifest",
        "probable_cause": "",
        "suggested_remediation": ""
      }
    ],
    "ErrCannotExposeObjectErrCode": [
      {
        "name": "ErrCannotExposeObjectErrCode",
        "code": "",
        "severity": "Alert",
        "long_description": "",
        "short_description": "cannot expose a ",
        "probable_cause": "",
        "suggested_remediation": ""
      }
    ],
    "ErrConnectCode": [
      {
        "name": "ErrConnectCode",
        "code": "",
        "severity": "Alert",
        "long_description": "",
        "short_description": "Connection to broker failed",
        "probable_cause": "",
        "suggested_remediation": ""
      }
    ],
    "ErrConstructingRestHelperCode": [
      {
        "name": "ErrConstructingRestHelperCode",
        "code": "",
        "severity": "Alert",
        "long_description": "",
        "short_description": "",
        "probable_cause": "",
        "suggested_remediation": ""
      }
    ],
    "ErrCreatingServiceCode": [
      {
        "name": "ErrCreatingServiceCode",
        "code": "",
        "severity": "Alert",
        "long_description": "",
        "short_description": "",
        "probable_cause": "",
        "suggested_remediation": ""
      }
    ],
    "ErrDatabaseOpenCode": [
      {
        "name": "ErrDatabaseOpenCode",
        "code": "",
        "severity": "Alert",
        "long_description": "",
        "short_description": "Unable to open database",
        "probable_cause": "",
        "suggested_remediation": ""
      }
    ],
    "ErrEmptyConfigCode": [
      {
        "name": "ErrEmptyConfigCode",
        "code": "",
        "severity": "Alert",
        "long_description": "",
        "short_description": "Config not initialized",
        "probable_cause": "",
        "suggested_remediation": ""
      }
    ],
    "ErrEncodedConnCode": [
      {
        "name": "ErrEncodedConnCode",
        "code": "",
        "severity": "Alert",
        "long_description": "",
        "short_description": "Encoding connection failed with broker",
        "probable_cause": "",
        "suggested_remediation": ""
      }
    ],
    "ErrEndpointNotFoundCode": [
      {
        "name": "ErrEndpointNotFoundCode",
        "code": "",
        "severity": "Alert",
        "long_description": "",
        "short_description": "Unable to discover an endpoint",
        "probable_cause": "",
        "suggested_remediation": ""
      }
    ],
    "ErrExposeResourceCode": [
      {
        "name": "ErrExposeResourceCode",
        "code": "",
        "severity": "Alert",
        "long_description": "",
        "short_description": "",
        "probable_cause": "",
        "suggested_remediation": ""
      }
    ],
    "ErrFailedToExtractPodSelectorErrCode": [
      {
        "name": "ErrFailedToExtractPodSelectorErrCode",
        "code": "",
        "severity": "Alert",
        "long_description": "",
        "short_description": "cannot extract pod selector from ",
        "probable_cause": "",
        "suggested_remediation": ""
      }
    ],
    "ErrFailedToExtractPortsCode": [
      {
        "name": "ErrFailedToExtractPortsCode",
        "code": "",
        "severity": "Alert",
        "long_description": "",
        "short_description": "cannot extract ports from ",
        "probable_cause": "",
        "suggested_remediation": ""
      }
    ],
    "ErrFailedToExtractProtocolsErrCode": [
      {
        "name": "ErrFailedToExtractProtocolsErrCode",
        "code": "",
        "severity": "Alert",
        "long_description": "",
        "short_description": "cannot extract protocols from ",
        "probable_cause": "",
        "suggested_remediation": ""
      }
    ],
    "ErrGenerateServiceCode": [
      {
        "name": "ErrGenerateServiceCode",
        "code": "",
        "severity": "Alert",
        "long_description": "",
        "short_description": "",
        "probable_cause": "",
        "suggested_remediation": ""
      }
    ],
    "ErrGetBoolCode": [
      {
        "name": "ErrGetBoolCode",
        "code": "",
        "severity": "Alert",
        "long_description": "",
        "short_description": "Error while getting Boolean value for key: %s, error: %s",
        "probable_cause": "",
        "suggested_remediation": ""
      }
    ],
    "ErrGettingResourceCode": [
      {
        "name": "ErrGettingResourceCode",
        "code": "",
        "severity": "Alert",
        "long_description": "",
        "short_description": "",
        "probable_cause": "",
        "suggested_remediation": ""
      }
    ],
    "ErrInMemCode": [
      {
        "name": "ErrInMemCode",
        "code": "",
        "severity": "Fatal",
        "long_description": "",
        "short_description": "InMem configuration initialization failed",
        "probable_cause": "",
        "suggested_remediation": ""
      }
    ],
    "ErrInvalidAPIServerCode": [
      {
        "name": "ErrInvalidAPIServerCode",
        "code": "",
        "severity": "Alert",
        "long_description": "",
        "short_description": "Invalid API Server URL",
        "probable_cause": "",
        "suggested_remediation": ""
      }
    ],
    "ErrInvalidDeploymentNoSelectorsCode": [
      {
        "name": "ErrInvalidDeploymentNoSelectorsCode",
        "code": "",
        "severity": "Alert",
        "long_description": "",
        "short_description": "invalid deployment: no selectors, therefore cannot be exposed",
        "probable_cause": "",
        "suggested_remediation": ""
      }
    ],
    "ErrInvalidDeploymentNoSelectorsLabelsCode": [
      {
        "name": "ErrInvalidDeploymentNoSelectorsLabelsCode",
        "code": "",
        "severity": "Alert",
        "long_description": "",
        "short_description": "the deployment has no labels or selectors and cannot be exposed",
        "probable_cause": "",
        "suggested_remediation": ""
      }
    ],
    "ErrInvalidProtocolCode": [
      {
        "name": "ErrInvalidProtocolCode",
        "code": "",
        "severity": "Alert",
        "long_description": "",
        "short_description": "invalid protocol: only http, https and file are valid protocols",
        "probable_cause": "",
        "suggested_remediation": ""
      }
    ],
    "ErrInvalidReplicaNoSelectorsLabelsCode": [
      {
        "name": "ErrInvalidReplicaNoSelectorsLabelsCode",
        "code": "",
        "severity": "Alert",
        "long_description": "",
        "short_description": "the replica set has no labels or selectors and cannot be exposed",
        "probable_cause": "",
        "suggested_remediation": ""
      }
    ],
    "ErrInvalidReplicaSetNoSelectorsCode": [
      {
        "name": "ErrInvalidReplicaSetNoSelectorsCode",
        "code": "",
        "severity": "Alert",
        "long_description": "",
        "short_description": "invalid replicaset: no selectors, therefore cannot be exposed",
        "probable_cause": "",
        "suggested_remediation": ""
      }
    ],
    "ErrLableBasedMapCode": [
      {
        "name": "ErrLableBasedMapCode",
        "code": "",
        "severity": "Alert",
        "long_description": "",
        "short_description": "",
        "probable_cause": "",
        "suggested_remediation": ""
      }
    ],
    "ErrLoadConfigCode": [
      {
        "name": "ErrLoadConfigCode",
        "code": "",
        "severity": "Alert",
        "long_description": "",
        "short_description": "Error loading kubernetes config",
        "probable_cause": "",
        "suggested_remediation": ""
      }
    ],
    "ErrMarshalCode": [
      {
        "name": "ErrMarshalCode",
        "code": "",
        "severity": "Alert",
        "long_description": "",
        "short_description": "Marshal error, Description: %s",
        "probable_cause": "",
        "suggested_remediation": ""
      }
    ],
    "ErrMatchExpressionsConvertionErrCode": [
      {
        "name": "ErrMatchExpressionsConvertionErrCode",
        "code": "",
        "severity": "Alert",
        "long_description": "",
        "short_description": "couldn't convert expressions - to map-based selector format",
        "probable_cause": "",
        "suggested_remediation": ""
      }
    ],
    "ErrNewDiscoveryCode": [
      {
        "name": "ErrNewDiscoveryCode",
        "code": "",
        "severity": "Alert",
        "long_description": "",
        "short_description": "Error creating discovery client",
        "probable_cause": "",
        "suggested_remediation": ""
      }
    ],
    "ErrNewDynClientCode": [
      {
        "name": "ErrNewDynClientCode",
        "code": "",
        "severity": "Alert",
        "long_description": "",
        "short_description": "Error creating dynamic client",
        "probable_cause": "",
        "suggested_remediation": ""
      }
    ],
    "ErrNewInformerCode": [
      {
        "name": "ErrNewInformerCode",
        "code": "",
        "severity": "Alert",
        "long_description": "",
        "short_description": "Error creating informer client",
        "probable_cause": "",
        "suggested_remediation": ""
      }
    ],
    "ErrNewKubeClientCode": [
      {
        "name": "ErrNewKubeClientCode",
        "code": "",
        "severity": "Alert",
        "long_description": "",
        "short_description": "Error creating kubernetes clientset",
        "probable_cause": "",
        "suggested_remediation": ""
      }
    ],
    "ErrNoPortsFoundForHeadlessResourceCode": [
      {
        "name": "ErrNoPortsFoundForHeadlessResourceCode",
        "code": "",
        "severity": "Alert",
        "long_description": "",
        "short_description": "no ports found for the non headless resource",
        "probable_cause": "",
        "suggested_remediation": ""
      }
    ],
    "ErrNoneDatabaseCode": [
      {
        "name": "ErrNoneDatabaseCode",
        "code": "",
        "severity": "Alert",
        "long_description": "",
        "short_description": "No Database selected",
        "probable_cause": "",
        "suggested_remediation": ""
      }
    ],
    "ErrPodHasNoLabelsCode": [
      {
        "name": "ErrPodHasNoLabelsCode",
        "code": "",
        "severity": "Alert",
        "long_description": "",
        "short_description": "the pod has no labels and cannot be exposed",
        "probable_cause": "",
        "suggested_remediation": ""
      }
    ],
    "ErrPortParsingCode": [
      {
        "name": "ErrPortParsingCode",
        "code": "",
        "severity": "Alert",
        "long_description": "",
        "short_description": "",
        "probable_cause": "",
        "suggested_remediation": ""
      }
    ],
    "ErrProtocolBasedMapCode": [
      {
        "name": "ErrProtocolBasedMapCode",
        "code": "",
        "severity": "Alert",
        "long_description": "",
        "short_description": "",
        "probable_cause": "",
        "suggested_remediation": ""
      }
    ],
    "ErrPublishCode": [
      {
        "name": "ErrPublishCode",
        "code": "",
        "severity": "Alert",
        "long_description": "",
        "short_description": "Publish failed",
        "probable_cause": "",
        "suggested_remediation": ""
      }
    ],
    "ErrPublishRequestCode": [
      {
        "name": "ErrPublishRequestCode",
        "code": "",
        "severity": "Alert",
        "long_description": "",
        "short_description": "Publish request failed",
        "probable_cause": "",
        "suggested_remediation": ""
      }
    ],
    "ErrQueueSubscribeCode": [
      {
        "name": "ErrQueueSubscribeCode",
        "code": "",
        "severity": "Alert",
        "long_description": "",
        "short_description": "Subscription failed",
        "probable_cause": "",
        "suggested_remediation": ""
      }
    ],
    "ErrReadingLocalFileCode": [
      {
        "name": "ErrReadingLocalFileCode",
        "code": "",
        "severity": "Alert",
        "long_description": "",
        "short_description": "error reading local file",
        "probable_cause": "",
        "suggested_remediation": ""
      }
    ],
    "ErrReadingRemoteFileCode": [
      {
        "name": "ErrReadingRemoteFileCode",
        "code": "",
        "severity": "Alert",
        "long_description": "",
        "short_description": "error reading remote file",
        "probable_cause": "",
        "suggested_remediation": ""
      }
    ],
    "ErrRemoteFileNotFoundCode": [
      {
        "name": "ErrRemoteFileNotFoundCode",
        "code": "",
        "severity": "Alert",
        "long_description": "",
        "short_description": "remote file not found at",
        "probable_cause": "",
        "suggested_remediation": ""
      }
    ],
    "ErrResourceCannotBeExposedCode": [
      {
        "name": "ErrResourceCannotBeExposedCode",
        "code": "",
        "severity": "Alert",
        "long_description": "",
        "short_description": "resource type %s cannot be exposed: ",
        "probable_cause": "",
        "suggested_remediation": ""
      }
    ],
    "ErrSQLMapMarshalValueCode": [
      {
        "name": "ErrSQLMapMarshalValueCode",
        "code": "",
        "severity": "Alert",
        "long_description": "",
        "short_description": "failed to marshal value",
        "probable_cause": "",
        "suggested_remediation": ""
      }
    ],
    "ErrSQLMapUnmarshalJSONCode": [
      {
        "name": "ErrSQLMapUnmarshalJSONCode",
        "code": "",
        "severity": "Alert",
        "long_description": "",
        "short_description": "failed to unmarshal json",
        "probable_cause": "",
        "suggested_remediation": ""
      }
    ],
    "ErrSQLMapUnmarshalScannedCode": [
      {
        "name": "ErrSQLMapUnmarshalScannedCode",
        "code": "",
        "severity": "Alert",
        "long_description": "",
        "short_description": "invalid data type: expected []byte",
        "probable_cause": "",
        "suggested_remediation": ""
      },
      {
        "name": "ErrSQLMapUnmarshalScannedCode",
        "code": "",
        "severity": "Alert",
        "long_description": "",
        "short_description": "failed to unmarshal scanned data",
        "probable_cause": "",
        "suggested_remediation": ""
      }
    ],
    "ErrSQLMapUnmarshalTextCode": [
      {
        "name": "ErrSQLMapUnmarshalTextCode",
        "code": "",
        "severity": "Alert",
        "long_description": "",
        "short_description": "failed to unmarshal text",
        "probable_cause": "",
        "suggested_remediation": ""
      }
    ],
    "ErrSelectorBasedMapCode": [
      {
        "name": "ErrSelectorBasedMapCode",
        "code": "",
        "severity": "Alert",
        "long_description": "",
        "short_description": "",
        "probable_cause": "",
        "suggested_remediation": ""
      }
    ],
    "ErrServiceDiscoveryCode": [
      {
        "name": "ErrServiceDiscoveryCode",
        "code": "",
        "severity": "Alert",
        "long_description": "",
        "short_description": "Error Discovering service",
        "probable_cause": "",
        "suggested_remediation": ""
      }
    ],
    "ErrServiceHasNoSelectorsCode": [
      {
        "name": "ErrServiceHasNoSelectorsCode",
        "code": "",
        "severity": "Alert",
        "long_description": "",
        "short_description": "the service has no pod selector set",
        "probable_cause": "",
        "suggested_remediation": ""
      }
    ],
    "ErrTraverserCode": [
      {
        "name": "ErrTraverserCode",
        "code": "",
        "severity": "Alert",
        "long_description": "",
        "short_description": "",
        "probable_cause": "",
        "suggested_remediation": ""
      }
    ],
    "ErrUnknownSessionAffinityErrCode": [
      {
        "name": "ErrUnknownSessionAffinityErrCode",
        "code": "",
        "severity": "Alert",
        "long_description": "",
        "short_description": "unknown session affinity:",
        "probable_cause": "",
        "suggested_remediation": ""
      }
    ],
    "ErrUnmarshalCode": [
      {
        "name": "ErrUnmarshalCode",
        "code": "",
        "severity": "Alert",
        "long_description": "",
        "short_description": "Unmarshal unknown error: %s",
        "probable_cause": "",
        "suggested_remediation": ""
      }
    ],
    "ErrUnmarshalInvalidCode": [
      {
        "name": "ErrUnmarshalInvalidCode",
        "code": "",
        "severity": "Alert",
        "long_description": "",
        "short_description": "Unmarshal invalid error for type: ",
        "probable_cause": "",
        "suggested_remediation": ""
      }
    ],
    "ErrUnmarshalSyntaxCode": [
      {
        "name": "ErrUnmarshalSyntaxCode",
        "code": "",
        "severity": "Alert",
        "long_description": "",
        "short_description": "Unmarshal syntax error at offest: ",
        "probable_cause": "",
        "suggested_remediation": ""
      }
    ],
    "ErrUnmarshalTypeCode": [
      {
        "name": "ErrUnmarshalTypeCode",
        "code": "",
        "severity": "Alert",
        "long_description": "",
        "short_description": "Unmarshal type error at key: %s. Error: %s",
        "probable_cause": "",
        "suggested_remediation": ""
      }
    ],
    "ErrUnmarshalUnsupportedTypeCode": [
      {
        "name": "ErrUnmarshalUnsupportedTypeCode",
        "code": "",
        "severity": "Alert",
        "long_description": "",
        "short_description": "Unmarshal unsupported type error at key: ",
        "probable_cause": "",
        "suggested_remediation": ""
      }
    ],
    "ErrUnmarshalUnsupportedValueCode": [
      {
        "name": "ErrUnmarshalUnsupportedValueCode",
        "code": "",
        "severity": "Alert",
        "long_description": "",
        "short_description": "Unmarshal unsupported value error at key: ",
        "probable_cause": "",
        "suggested_remediation": ""
      }
    ],
    "ErrValidateConfigCode": [
      {
        "name": "ErrValidateConfigCode",
        "code": "",
        "severity": "Alert",
        "long_description": "",
        "short_description": "Validation failed in the kubernetes config",
        "probable_cause": "",
        "suggested_remediation": ""
      }
    ],
    "ErrViperCode": [
      {
        "name": "ErrViperCode",
        "code": "",
        "severity": "Fatal",
        "long_description": "",
        "short_description": "Viper configuration initialization failed",
        "probable_cause": "",
        "suggested_remediation": ""
      }
    ]
  }
}